README.md
setup.py
src/_str_version.py
src/client.py
src/client_methods.py
src/transaction_builder.py
src/transaction_builder_methods.py
src/Avalara_Python_SDK.egg-info/PKG-INFO
src/Avalara_Python_SDK.egg-info/SOURCES.txt
src/Avalara_Python_SDK.egg-info/dependency_links.txt
src/Avalara_Python_SDK.egg-info/requires.txt
src/Avalara_Python_SDK.egg-info/top_level.txt