Metadata-Version: 2.1
Name: Avalara-Python-SDK
Version: 0.0.0
Summary: Avalara Tax Python SDK.
Home-page: UNKNOWN
Author: Han Bao, Adrienne Karnoski, Robert Bronson, Philip Werner
Author-email: han.bao@avalara.com
License: UNKNOWN
Platform: UNKNOWN
Provides-Extra: test
